{
   "CodeGenerationMode": 4,
   "ContextClassName": "SportsLendDBContext",
   "ContextNamespace": null,
   "FilterSchemas": false,
   "IncludeConnectionString": true,
   "MinimumProductVersion": "2.6.1186",
   "ModelNamespace": null,
   "OutputContextPath": null,
   "OutputPath": "Models",
   "PreserveCasingWithRegex": true,
   "ProjectRootNamespace": "SportsLend.DAL",
   "Schemas": null,
   "SelectedHandlebarsLanguage": 2,
   "SelectedToBeGenerated": 0,
   "T4TemplatePath": null,
   "Tables": [
      {
         "Name": "[dbo].[Equipment]",
         "ObjectType": 0
      },
      {
         "Name": "[dbo].[EquipmentTypes]",
         "ObjectType": 0
      },
      {
         "Name": "[dbo].[Loans]",
         "ObjectType": 0
      },
      {
         "Name": "[dbo].[Members]",
         "ObjectType": 0
      },
      {
         "Name": "[dbo].[Users]",
         "ObjectType": 0
      }
   ],
   "UiHint": null,
   "UncountableWords": null,
   "UseAsyncStoredProcedureCalls": true,
   "UseBoolPropertiesWithoutDefaultSql": false,
   "UseDatabaseNames": false,
   "UseDatabaseNamesForRoutines": true,
   "UseDateOnlyTimeOnly": true,
   "UseDbContextSplitting": false,
   "UseDecimalDataAnnotationForSprocResult": true,
   "UseFluentApiOnly": true,
   "UseHandleBars": false,
   "UseHierarchyId": false,
   "UseInflector": true,
   "UseInternalAccessModifiersForSprocsAndFunctions": false,
   "UseLegacyPluralizer": false,
   "UseManyToManyEntity": false,
   "UseNoDefaultConstructor": false,
   "UseNoNavigations": false,
   "UseNoObjectFilter": false,
   "UseNodaTime": false,
   "UseNullableReferences": false,
   "UsePrefixNavigationNaming": false,
   "UseSchemaFolders": false,
   "UseSchemaNamespaces": false,
   "UseSpatial": false,
   "UseT4": false,
   "UseT4Split": false
}